ultimate_hosts_blacklist_the_whitelist/__init__.py
ultimate_hosts_blacklist_the_whitelist/core.py
ultimate_hosts_blacklist_the_whitelist/helpers.py
ultimate_hosts_blacklist_the_whitelist-1.0.2.dist-info/LICENSE
ultimate_hosts_blacklist_the_whitelist-1.0.2.dist-info/METADATA
ultimate_hosts_blacklist_the_whitelist-1.0.2.dist-info/WHEEL
ultimate_hosts_blacklist_the_whitelist-1.0.2.dist-info/entry_points.txt
ultimate_hosts_blacklist_the_whitelist-1.0.2.dist-info/top_level.txt
ultimate_hosts_blacklist_the_whitelist-1.0.2.dist-info/RECORD
