Metadata-Version: 2.1
Name: ultimate-hosts-blacklist-the-whitelist
Version: 1.0.2
Summary: The whitelisting tool of the Ultimate Hosts Blacklist project.
Home-page: https://github.com/Ultimate-Hosts-Blacklist/whitelist/tree/script
Author: funilrys
Author-email: contact@funilrys.com
License: MIT
Keywords: Python,hosts,hosts file,whitelist
Platform: any
Classifier: Environment :: Console
Classifier: Topic :: Internet
Classifier: Development Status :: 5 - Production/Stable
Classifier: Intended Audience :: Developers
Classifier: Programming Language :: Python
Classifier: Programming Language :: Python :: 3
Classifier: License :: OSI Approved :: MIT License
Requires-Dist: requests (>=2.21.0)
Requires-Dist: domain2idna (>=1.6.1)
Requires-Dist: colorama (>=0.4.1)
